{
  "schemaVersion": 1,
  "theme": "quiet archive nook",
  "styleSource": {
    "petId": "gakju",
    "displayName": "Gakju / \uac01\uc8fc",
    "description": "A tiny calm female librarian-researcher companion born from books, paper scraps, ink, and terminal fragments."
  },
  "geometry": {
    "roomWidth": 384,
    "roomHeight": 240,
    "cellWidth": 192,
    "cellHeight": 208
  },
  "desiredProps": [
    "desk",
    "book-stack"
  ],
  "promptConstraints": [
    "SD/chibi dollhouse room",
    "eye-level side view",
    "384x240 room source",
    "no readable text",
    "no letters",
    "no numbers",
    "no watermark",
    "no UI frame",
    "no character in the room background"
  ]
}